tcat_gtfs_csv_validator/__init__.py
tcat_gtfs_csv_validator/example_use.py
tcat_gtfs_csv_validator/exceptions.py
tcat_gtfs_csv_validator/gcv_support.py
tcat_gtfs_csv_validator/gcv_test_release.py
tcat_gtfs_csv_validator/version.py
tcat_gtfs_csv_validator/rules/gtfs_flex_v2.0_rules.csv
tcat_gtfs_csv_validator/rules/gtfs_pathways_v1.0_rules.csv
tcat_gtfs_csv_validator/schemas/gtfs_flex/v2.0/booking_rules_schema.csv
tcat_gtfs_csv_validator/schemas/gtfs_flex/v2.0/location_groups_schema.csv
tcat_gtfs_csv_validator/schemas/gtfs_flex/v2.0/locations_geojson_jsonschema.json
tcat_gtfs_csv_validator/schemas/gtfs_flex/v2.0/stop_times_schema.csv
tcat_gtfs_csv_validator/schemas/gtfs_pathways/v1.0/levels_schema.csv
tcat_gtfs_csv_validator/schemas/gtfs_pathways/v1.0/pathways_schema.csv
tcat_gtfs_csv_validator/schemas/gtfs_pathways/v1.0/stops_schema.csv
tcat_gtfs_csv_validator-0.0.40.dist-info/LICENSE
tcat_gtfs_csv_validator-0.0.40.dist-info/METADATA
tcat_gtfs_csv_validator-0.0.40.dist-info/WHEEL
tcat_gtfs_csv_validator-0.0.40.dist-info/top_level.txt
tcat_gtfs_csv_validator-0.0.40.dist-info/RECORD
