Metadata-Version: 2.1
Name: tcat-gtfs-csv-validator
Version: 0.0.40
Summary: Scripts to validate GTFS csv files. Focused on Flex and Pathways extensions
Home-page: https://github.com/TaskarCenterAtUW/TDEI-gtfs-csv-validator
Author: Sujata Misra
Author-email: sujatam@gaussiansolutions.com
Project-URL: Documentation, https://github.com/TaskarCenterAtUW/TDEI-gtfs-csv-validator/blob/main/README.md
Project-URL: GitHub, https://github.com/TaskarCenterAtUW/TDEI-gtfs-csv-validator
Project-URL: Changelog, https://github.com/TaskarCenterAtUW/TDEI-gtfs-csv-validator/blob/main/CHANGELOG.md
Classifier: Programming Language :: Python :: 3
Classifier: License :: OSI Approved :: MIT License
Classifier: Operating System :: OS Independent
Requires-Python: >=3.10
License-File: LICENSE
Requires-Dist: pandas~=2.2.2
Requires-Dist: jsonschema~=4.23.0
